discover/__init__.py
discover/app.py
discover/backend/__init__.py
discover/backend/virtual_environment.py
discover/data/__init__.py
discover/data/adjectives.py
discover/data/animals.py
discover/data/colors.py
discover/data/countries.py
discover/data/languages.py
discover/data/names.py
discover/data/star_wars.py
discover/exec/__init__.py
discover/exec/execution_handler.py
discover/route/__init__.py
discover/route/cancel.py
discover/route/cml_info.py
discover/route/explain.py
discover/route/extract.py
discover/route/fetch_result.py
discover/route/log.py
discover/route/predict.py
discover/route/process.py
discover/route/status.py
discover/route/train.py
discover/route/ui.py
discover/route/upload.py
discover/templates/__init__.py
discover/templates/ajax_template.html
discover/templates/base.html
discover/templates/index.html
discover/utils/__init__.py
discover/utils/env.py
discover/utils/import_utils.py
discover/utils/job_utils.py
discover/utils/log_utils.py
discover/utils/thread_utils.py
discover/utils/venv_utils.py
docs/docsource/conf.py
hcai_discover-1.0.7.dist-info/licenses/LICENSE
hcai_discover-1.0.7.dist-info/METADATA
hcai_discover-1.0.7.dist-info/WHEEL
hcai_discover-1.0.7.dist-info/entry_points.txt
hcai_discover-1.0.7.dist-info/top_level.txt
hcai_discover-1.0.7.dist-info/RECORD
