Metadata-Version: 2.4
Name: hcai-discover
Version: 1.0.7
Summary: DISCOVER is a lightweight server designed to create and manage machine learning jobs based on requests.
Author-email: Dominik Schiller <dominik.schiller@uni-a.de>, Tobias Hallmen <tobias.hallmen@uni-a.de>, Tobias Baur <tobias.baur@uni-a.de>, Fabio Hellmann <fabio.hellmann@uni-a.de>
Project-URL: Documentation, https://hcmlab.github.io/discover
Project-URL: Repository, https://github.com/hcmlab/discover
Keywords: DISCOVER,NOVA,machine learning
Classifier: Development Status :: 4 - Beta
Classifier: Programming Language :: Python
Classifier: Intended Audience :: Developers
Classifier: Topic :: Software Development :: Build Tools
Classifier: License :: OSI Approved :: MIT License
Classifier: Programming Language :: Python :: 3.9
Classifier: Programming Language :: Python :: 3.10
Classifier: Programming Language :: Python :: 3 :: Only
Requires-Python: >=3.9
License-File: LICENSE
Requires-Dist: flask==3.0.0
Requires-Dist: hcai-discover-utils
Requires-Dist: cheroot
Requires-Dist: python-dotenv
Requires-Dist: psutil
Requires-Dist: numpy<2.0,>=1.24
Requires-Dist: toml
Dynamic: license-file
